{"allLayersCount":"Todas las capas ({count})","collapseAll":"Contraer todo","deselectFeature":"Anular selección de entidad","deselectGroup":"Anular selección de grupo","deselectLayer":"Anular selección de capa","featuresCount":"Entidades: {count}","featuresCountShowing":"Entidades: {count}, Presentación: {visibleCount}","filter":"Filtrar","filterByLayer":"Filtrar por capa","noMatchingFeatures":"No hay entidades coincidentes","onlySelectFeature":"Seleccionar solo esta entidad","onlySelectThis":"Seleccionar solo esto","selection":"Selección","selectionCount":"Selección ({count})","tooManyFeatures":"Las entidades son demasiadas para mostrarlas en esta lista.","untitledLayer":"Capa sin título","untitledFeature":"Entidad sin título","widgetLabel":"Lista de selección","zoomTo":"Acercar"}