{"measures":{"length":"Lengde","area":"Areal","volume":"Volum","angle":"Vinkel"},"systems":{"metric":"å_Metric_____________ø","imperial":"å_Imperial_________________ø"},"units":{"millimeters":{"singular":"millimeter","singularCapitalized":"å_Millimeter_____________________ø","plural":"millimeter","pluralCapitalized":"å_Millimeters____________ø","abbr":"mm"},"centimeters":{"singular":"centimeter","singularCapitalized":"å_Centimeter_____________________ø","plural":"centimeter","pluralCapitalized":"å_Centimeters____________ø","abbr":"cm"},"decimeters":{"singular":"desimeter","singularCapitalized":"å_Decimeter___________________ø","plural":"desimeter","pluralCapitalized":"å_Decimeter___________________ø","abbr":"dm"},"meters":{"singular":"meter","singularCapitalized":"å_Meter___________ø","plural":"meter","pluralCapitalized":"å_Meters_____________ø","abbr":"m"},"kilometers":{"singular":"kilometer","singularCapitalized":"å_Kilometer___________________ø","plural":"kilometer","pluralCapitalized":"å_Kilometers_____________________ø","abbr":"km"},"inches":{"singular":"tomme","singularCapitalized":"å_Inch_________ø","plural":"tommer","pluralCapitalized":"å_Inches_____________ø","abbr":"tm"},"feet":{"singular":"fot","singularCapitalized":"å_Foot_________ø","plural":"fot","pluralCapitalized":"å_Feet_________ø","abbr":"ft"},"yards":{"singular":"yard","singularCapitalized":"å_Yard_________ø","plural":"yard","pluralCapitalized":"å_Yards___________ø","abbr":"yd"},"miles":{"singular":"mile","singularCapitalized":"å_Mile_________ø","plural":"miles","pluralCapitalized":"å_Miles___________ø","abbr":"mi"},"nautical-miles":{"singular":"nautisk mil","singularCapitalized":"å_Nautical mile______________ø","plural":"nautiske mil","pluralCapitalized":"å_Nautical miles_______________ø","abbr":"nm"},"us-feet":{"singular":"fot (USA)","singularCapitalized":"å_Foot (US)___________________ø","plural":"fot (USA)","pluralCapitalized":"å_Feet (US)___________________ø","abbr":"ft"},"square-millimeters":{"singular":"kvadratmillimeter","singularCapitalized":"å_Square millimeter__________________ø","plural":"kvadratmillimeter","pluralCapitalized":"å_Square millimeters___________________ø","abbr":"mm²"},"square-centimeters":{"singular":"kvadratcentimeter","singularCapitalized":"å_Square centimeter__________________ø","plural":"kvadratcentimeter","pluralCapitalized":"å_Square centimeters___________________ø","abbr":"cm²"},"square-decimeters":{"singular":"kvadratdesimeter","singularCapitalized":"å_Square decimeter_________________ø","plural":"kvadratdesimeter","pluralCapitalized":"å_Square decimeters__________________ø","abbr":"dm²"},"square-meters":{"singular":"kvadratmeter","singularCapitalized":"å_Square meter_____________ø","plural":"kvadratmeter","pluralCapitalized":"å_Square meters______________ø","abbr":"m²"},"square-kilometers":{"singular":"kvadratkilometer","singularCapitalized":"å_Square kilometer_________________ø","plural":"kvadratkilometer","pluralCapitalized":"å_Square kilometers__________________ø","abbr":"km²"},"square-inches":{"singular":"kvadrattommer","singularCapitalized":"å_Square inch____________ø","plural":"kvadrattommer","pluralCapitalized":"å_Square inches______________ø","abbr":"in²"},"square-feet":{"singular":"kvadratfot","singularCapitalized":"å_Square foot____________ø","plural":"kvadratfot","pluralCapitalized":"å_Square feet____________ø","abbr":"ft²"},"square-yards":{"singular":"kvadratyard","singularCapitalized":"å_Square yard____________ø","plural":"kvadratyard","pluralCapitalized":"å_Square yards_____________ø","abbr":"yd²"},"square-miles":{"singular":"kvadratmiles","singularCapitalized":"å_Square mile____________ø","plural":"kvadratmiles","pluralCapitalized":"å_Square miles_____________ø","abbr":"mi²"},"square-us-feet":{"singular":"kvadratfot (USA)","singularCapitalized":"å_Square foot (US)_________________ø","plural":"kvadratfot (USA)","pluralCapitalized":"å_Square feet (US)_________________ø","abbr":"ft²"},"acres":{"singular":"acre","singularCapitalized":"å_Acre_________ø","plural":"acre","pluralCapitalized":"å_Acres___________ø","abbr":"acre"},"ares":{"singular":"ar","singularCapitalized":"å_Are_______ø","plural":"ar","pluralCapitalized":"å_Ares_________ø","abbr":"a"},"hectares":{"singular":"hektar","singularCapitalized":"å_Hectare_______________ø","plural":"hektar","pluralCapitalized":"å_Hectares_________________ø","abbr":"ha"},"liters":{"singular":"liter","singularCapitalized":"å_Liter___________ø","plural":"liter","pluralCapitalized":"å_Liters_____________ø","abbr":"l"},"cubic-millimeters":{"singular":"kubikkmillimeter","singularCapitalized":"å_Cubic millimeter_________________ø","plural":"kubikkmillimeter","pluralCapitalized":"å_Cubic millimeters__________________ø","abbr":"mm³"},"cubic-centimeters":{"singular":"kubikkcentimeter","singularCapitalized":"å_Cubic centimeter_________________ø","plural":"kubikkcentimeter","pluralCapitalized":"å_Cubic centimeters__________________ø","abbr":"cm³"},"cubic-decimeters":{"singular":"kubikkdesimeter","singularCapitalized":"å_Cubic decimeter________________ø","plural":"kubikkdesimeter","pluralCapitalized":"å_Cubic decimeters_________________ø","abbr":"dm³"},"cubic-meters":{"singular":"kubikkmeter","singularCapitalized":"å_Cubic meter____________ø","plural":"kubikkmeter","pluralCapitalized":"å_Cubic meters_____________ø","abbr":"m³"},"cubic-kilometers":{"singular":"kubikkilometer","singularCapitalized":"å_Cubic kilometer________________ø","plural":"kubikkilometer","pluralCapitalized":"å_Cubic kilometers_________________ø","abbr":"km³"},"cubic-inches":{"singular":"kubikktomme","singularCapitalized":"å_Cubic inch_____________________ø","plural":"kubikktommer","pluralCapitalized":"å_Cubic inches_____________ø","abbr":"in³"},"cubic-feet":{"singular":"kubikkfot","singularCapitalized":"å_Cubic foot_____________________ø","plural":"kubikkfot","pluralCapitalized":"å_Cubic feet_____________________ø","abbr":"ft³"},"cubic-yards":{"singular":"kubikkyard","singularCapitalized":"å_Cubic yard_____________________ø","plural":"kubikkyard","pluralCapitalized":"å_Cubic yards____________ø","abbr":"yd³"},"cubic-miles":{"singular":"kubikkmile","singularCapitalized":"å_Cubic mile_____________________ø","plural":"kubikkmiles","pluralCapitalized":"å_Cubic miles____________ø","abbr":"mi³"},"radians":{"singular":"radian","singularCapitalized":"å_Radian_____________ø","plural":"radianer","pluralCapitalized":"å_Radians_______________ø","abbr":""},"degrees":{"singular":"grad","singularCapitalized":"å_Degree_____________ø","plural":"grader","pluralCapitalized":"å_Degrees_______________ø","abbr":"°"},"bytes":{"B":"{fileSize} B","kB":"{fileSize} kB","MB":"{fileSize} MB","GB":"{fileSize} GB","TB":"{fileSize} TB"}}}