{"title":"Visor de imágenes orientadas","currentFootprint":"Huella actual","additionalFootprints":"Huellas adicionales","additionalCameraLocations":"Ubicaciones de cámaras adicionales","imageAttributes":"Atributos de imagen","imageEnhancement":"Mejora de imagen","imageGallery":"Galería de imágenes","float":"Flotante","dock":"Acoplar","footprint":"Huella","noImageError":"No hay ninguna imagen disponible para la ubicación seleccionada.","onLoadMessage":"Seleccione una ubicación en el mapa para ver las imágenes.","imageLoadError":"Se ha producido un error al cargar la imagen."}