{"title":"Zobrazovač orientovaných snímok","currentFootprint":"Aktuálny obrys rastra","additionalFootprints":"Doplnkové obrysy rastra","additionalCameraLocations":"Doplnkové pozície kamery","imageAttributes":"Atribúty snímky","imageEnhancement":"Vylepšenie obrazu","imageGallery":"Galéria snímok","float":"Float","dock":"Ukotviť","footprint":"Obrys","noImageError":"Pre vybranú lokalitu nie je dostupná žiadna snímka.","onLoadMessage":"Na zobrazenie snímok vyberte miesto v mape.","imageLoadError":"Pri načítaní snímky došlo k chybe."}