{"title":"Oriented-Imagery-Viewer","currentFootprint":"Aktueller Footprint","additionalFootprints":"Zusätzliche Footprints","additionalCameraLocations":"Zusätzliche Kamerapositionen","imageAttributes":"Bildattribute","imageEnhancement":"Bildverbesserung","imageGallery":"Bildergalerie","float":"Float","dock":"Verankern","footprint":"Footprint","noImageError":"Für die ausgewählte Position ist kein Bild verfügbar.","onLoadMessage":"Wählen Sie eine Position auf der Karte aus, um Bilddaten anzuzeigen.","imageLoadError":"Beim Laden des Bildes ist ein Fehler aufgetreten."}