{
  "layer": "Laag",
  "featureservice": "Objectservice",
  "mapservice": "Map service",
  "webmap": "Web Map",
  "webmapformat": "Webmap: {webMapTitle}",
  "item": "Item",
  "invoking": "Aanroepen",
  "fields": "Veldnamen",
  "values": "Waarden",
  "relationships": "Gerelateerde functies",
  "layers": "Lagen",
  "tables": "Tabellen",
  "geometry": "Geometrie",
  "dictionary": "Woordenboek",
  "feature": "Object",
  "featureset": "Functieset",
  "featuresetcollection": "Objectset verzameling",
  "oid": "Object ID",
  "number": "Getal",
  "string": "Tekenreeks",
  "date": "Datum",
  "blob": "Binair",
  "raster": "Raster",
  "guid": "GUID",
  "global-id": "Internationale ID",
  "xml": "XML",
  "function": "Functie",
  "domainvalues": "Domeinwaarden",
  "subtypes": "Subtypen",
  "domainvaluesfortypeformat": "{fieldName}- Domeinwaarden voor type \\'{typeName}\\'",
  "domainvaluesbysubtypes": "Domeinwaarden op subtypen"
}
